<?xml version="1.0" encoding="UTF-8"?>

<channel name="xfce4-terminal" version="1.0">
  <property name="background-mode" type="string" value="TERMINAL_BACKGROUND_TRANSPARENT"/>
  <property name="background-darkness" type="double" value="0.69999999999999996"/>
  <property name="color-foreground" type="string" value="#e1e1e5e5eaea"/>
  <property name="color-background" type="string" value="#141417171717"/>
  <property name="color-palette" type="string" value="#141717;#ca2800;#E5BD77;#f24e00;#1D3557;#1D3557;#75a7be;#6f8191;#3D4249;#f24e00;#DFD0BB;#f2630d;#45789d;#45789d;#b1e4e5;#e1e5ea"/>
  <property name="font-allow-bold" type="bool" value="false"/>
  <property name="font-name" type="string" value="Terminus 11"/>
  <property name="misc-always-show-tabs" type="bool" value="false"/>
  <property name="misc-bell" type="bool" value="false"/>
  <property name="misc-bell-urgent" type="bool" value="false"/>
  <property name="misc-borders-default" type="bool" value="true"/>
  <property name="misc-cursor-blinks" type="bool" value="false"/>
  <property name="misc-cursor-shape" type="string" value="TERMINAL_CURSOR_SHAPE_IBEAM"/>
  <property name="misc-default-geometry" type="string" value="80x24"/>
  <property name="misc-inherit-geometry" type="bool" value="false"/>
  <property name="misc-menubar-default" type="bool" value="false"/>
  <property name="misc-mouse-autohide" type="bool" value="false"/>
  <property name="misc-mouse-wheel-zoom" type="bool" value="true"/>
  <property name="misc-toolbar-default" type="bool" value="false"/>
  <property name="misc-confirm-close" type="bool" value="false"/>
  <property name="misc-cycle-tabs" type="bool" value="true"/>
  <property name="misc-tab-close-buttons" type="bool" value="true"/>
  <property name="misc-tab-close-middle-click" type="bool" value="true"/>
  <property name="misc-tab-position" type="string" value="GTK_POS_TOP"/>
  <property name="misc-highlight-urls" type="bool" value="true"/>
  <property name="misc-middle-click-opens-uri" type="bool" value="false"/>
  <property name="misc-copy-on-select" type="bool" value="false"/>
  <property name="misc-show-relaunch-dialog" type="bool" value="true"/>
  <property name="misc-rewrap-on-resize" type="bool" value="true"/>
  <property name="misc-slim-tabs" type="bool" value="false"/>
  <property name="misc-new-tab-adjacent" type="bool" value="false"/>
  <property name="misc-search-dialog-opacity" type="uint" value="100"/>
  <property name="misc-show-unsafe-paste-dialog" type="bool" value="true"/>
  <property name="scrolling-bar" type="string" value="TERMINAL_SCROLLBAR_NONE"/>
  <property name="scrolling-on-output" type="bool" value="false"/>
  <property name="tab-activity-color" type="string" value="#caca28280000"/>
</channel>
